LICENSE
MANIFEST.in
README.rst
setup.py
django_couchbase/__init__.py
django_couchbase/admin.py
django_couchbase/apps.py
django_couchbase/fields.py
django_couchbase/models.py
django_couchbase/tests.py
django_couchbase/views.py
django_couchbase.egg-info/PKG-INFO
django_couchbase.egg-info/SOURCES.txt
django_couchbase.egg-info/dependency_links.txt
django_couchbase.egg-info/top_level.txt
django_couchbase/migrations/__init__.py