Metadata-Version: 1.1
Name: django-couchbase
Version: 0.1
Summary: Django ORM for Couchbase.
Home-page: https://github.com/aswinkp/django-couchbase/
Author: Aswin Kumar K P
Author-email: kp.aswinkumar@gmail.com
License: MIT License
Download-URL: https://github.com/aswinkp/django-couchbase/tarball/0.1
Platform: UNKNOWN
Classifier: Environment :: Web Environment
Classifier: Framework :: Django
Classifier: Intended Audience :: Developers
Classifier: License :: OSI Approved :: MIT License
Classifier: Operating System :: OS Independent
Classifier: Programming Language :: Python
Classifier: Programming Language :: Python :: 3
Classifier: Programming Language :: Python :: 3.4
Classifier: Programming Language :: Python :: 3.5
Classifier: Topic :: Internet :: WWW/HTTP
Classifier: Topic :: Internet :: WWW/HTTP :: Dynamic Content
